vaporetto-0.3.2.dist-info/METADATA
vaporetto-0.3.2.dist-info/WHEEL
vaporetto-0.3.2.dist-info/licenses/LICENSE-APACHE
vaporetto-0.3.2.dist-info/licenses/LICENSE-MIT
vaporetto/__init__.py
vaporetto/__init__.pyi
vaporetto/py.typed
vaporetto/vaporetto.cpython-310-i386-linux-gnu.so
vaporetto-0.3.2.dist-info/RECORD
