Metadata-Version: 2.4
Name: vaporetto
Version: 0.3.2
License-File: LICENSE-APACHE
License-File: LICENSE-MIT
Summary: Python wrapper of Vaporetto tokenizer
Home-Page: https://github.com/daac-tools/python-vaporetto
Author: Koichi Akabe <vbkaisetsu@gmail.com>
Author-email: Koichi Akabe <vbkaisetsu@gmail.com>
License: MIT OR Apache-2.0
Project-URL: Source Code, https://github.com/daac-tools/python-vaporetto
